LICENSE
MANIFEST.in
README.rst
requirements.txt
setup.py
tox.ini
django_celery_email_with_retry.egg-info/PKG-INFO
django_celery_email_with_retry.egg-info/SOURCES.txt
django_celery_email_with_retry.egg-info/dependency_links.txt
django_celery_email_with_retry.egg-info/not-zip-safe
django_celery_email_with_retry.egg-info/requires.txt
django_celery_email_with_retry.egg-info/top_level.txt
djcelery_email/__init__.py
djcelery_email/backends.py
djcelery_email/models.py
djcelery_email/tasks.py
test_project/__init__.py
test_project/manage.py
test_project/settings.py
test_project/test_runner.py
test_project/urls.py
test_project/tester/__init__.py
test_project/tester/models.py
test_project/tester/tests.py