Metadata-Version: 1.1
Name: django-celery-email-with-retry
Version: 1.0.3
Summary: Django email backend for celery.
Home-page: http://bitbucket.org/pmclanahan/django-celery-email
Author: Paul McLanahan
Author-email: paul@mclanahan.net
License: BSD
Platform: any
Classifier: Development Status :: 5 - Production/Stable
Classifier: Framework :: Django
Classifier: Operating System :: OS Independent
Classifier: Programming Language :: Python
Classifier: Programming Language :: Python :: 2.5
Classifier: Programming Language :: Python :: 2.6
Classifier: Programming Language :: Python :: 2.7
Classifier: Intended Audience :: Developers
Classifier: License :: OSI Approved :: BSD License
Classifier: Operating System :: POSIX
Classifier: Topic :: Communications
Classifier: Topic :: Communications :: Email
Classifier: Topic :: System :: Distributed Computing
Classifier: Topic :: Software Development :: Libraries :: Python Modules
